full-adder/fulladder.v
/*
Author: Sajeed Mohammad Shahriat
Affiliation: Rochester Institute of Technology
All rights reserved
This files can be reused and modified given that this copyright notice is not removed
*/

module full_adder (
	a,
	b,
	cin,
	sum,
	cout

); //end of port list

//---------------------------input ports-----------------------------
input a;
input b;
input cin;

//---------------------------output ports----------------------------
output sum;
output cout;

//-----------------------input port data type------------------------
wire a;
wire b;
wire cin;

//-----------------------output port data type-----------------------
reg sum;
reg cout;

//---------------------------RTL design------------------------------

always @ (a or b or cin)
	begin
		sum <= a^b^cin;
		cout <= ((a&b)|((a^b)&cin));
	end

endmodule

full-adder/fulladder_tb.v
/*
Author: Sajeed Mohammad Shahriat
Affiliation: Rochester Institute of Technology
All rights reserved
This files can be reused and modified given that this copyright notice is not removed
*/

module full_adder_tb ();

reg a, b, cin; //decllare all inputs as registers
wire sum, cout; //declare all outputs as wires

integer i, j, k; //integer required for running loops


initial
	begin
		$dumpfile ("full_adder_wave.vcd"); //required for gtkwaveform
		$dumpvars (0, full_adder_tb); //required for gtkwaveform

		$display ("time\t a b cin sum cout");
		$monitor ("%g\t %b %b %b\t %b  %b", $time, a, b, cin, sum, cout);
	a = 0; //initial value of a
	b = 0; //initial value of b
	cin = 0; //initial value of cin

//stimulus
	for ( i = 0; i< 2; i = i+1)
		begin
			for ( j = 0; j< 2; j = j+1)
				begin
					for ( k = 0; k< 2; k = k+1)
						begin
							#10 a= i; b= j; cin = k;
							#10 ;
						end
				end
		end

	end
full_adder connect_full_adder (
	a,
	b,
	cin,
	sum,
	cout
);

endmodule

full-adder/full_adder_wave.vcd
$date
	Thu Jul 20 14:46:00 2017
$end
$version
	Icarus Verilog
$end
$timescale
	1s
$end
$scope module full_adder_tb $end
$var wire 1 ! cout $end
$var wire 1 " sum $end
$var reg 1 # a $end
$var reg 1 $ b $end
$var reg 1 % cin $end
$var integer 32 & i [31:0] $end
$var integer 32 ' j [31:0] $end
$var integer 32 ( k [31:0] $end
$scope module connect_full_adder $end
$var wire 1 ) a $end
$var wire 1 * b $end
$var wire 1 + cin $end
$var reg 1 , cout $end
$var reg 1 - sum $end
$upscope $end
$upscope $end
$enddefinitions $end
#0
$dumpvars
0-
0,
0+
0*
0)
b0 (
b0 '
b0 &
0%
0$
0#
0"
0!
$end
#20
b1 (
#30
1-
1"
1%
1+
#40
b1 '
b0 (
#50
0%
0+
1$
1*
#60
b1 (
#70
1,
1!
0-
0"
1%
1+
#80
b1 &
b0 '
b0 (
#90
0,
0!
1-
1"
0%
0+
0$
0*
1#
1)
#100
b1 (
#110
1,
1!
0-
0"
1%
1+
#120
b1 '
b0 (
#130
0%
0+
1$
1*
#140
b1 (
#150
1-
1"
1%
1+
#160
b10 &
b10 '
b10 (
