d-flipflop/d-ff.v
/*
Author: Sajeed Mohammad Shahriat
Affiliation: Rochester Institute of Technology
All rights reserved
This files can be reused and modified given that this copyright notice is not removed
*/

module d_ff (
	data,	//data input
	q,	// data output	
	reset,	//reset signal
	clk	//clock
); //end of port list

//---------------------------input ports-----------------------------
input data;
input clk;
input reset;

//---------------------------output ports----------------------------
output q;

//-----------------------input port data type------------------------
wire data;
wire clk;
wire reset;

//-----------------------output port data type-----------------------
reg q;

//---------------------------RTL design------------------------------
always @ (posedge clk)
	if (reset == 1)
		begin
			q <= 1'b0;
		end
	else
		begin
			q <= data;
		end

endmodule //d-flipflop

d-flipflop/d-ff_tb.v
/*
Author: Sajeed Mohammad Shahriat
Affiliation: Rochester Institute of Technology
All rights reserved
This files can be reused and modified given that this copyright notice is not removed
*/

module d_ff_tb ();

reg data, reset, clk; //declare all inputs as registers
wire q; // declare all outputs as wires


always 
	begin	
		#100 clk = ~clk; //initialize clk
	end

initial
	begin
		$dumpfile ("d_ff_wave.vcd"); //required for gtkwaveform
		$dumpvars (0, d_ff_tb); //required for gtkwaveform

		$display ("time\t clk reset data q");
		$monitor ("%g\t %b %b %b", $time, clk, reset, data, q);
		clk = 1'b1; //initial value of clock		
		data = 1'b0; //initial value of data
		reset = 1'b0; //initial value of reset

//stimulus
	#100 data = 1'b1;
	#300 reset = 1'b1; 
	#300 reset = 1'b0;
	#600 data = 1'b0;
	#500 data = 1'b1;
	#200 data = 1'b0;
	#400 $finish;
	end

//connect DUT to test bench
d_ff connect_d_ff (
	data,
	q,	
	reset,	
	clk
);
endmodule

d-flipflop/d_ff_wave.vcd
$date
	Mon Jul 10 15:45:04 2017
$end
$version
	Icarus Verilog
$end
$timescale
	1s
$end
$scope module d_ff_tb $end
$var wire 1 ! q $end
$var reg 1 " clk $end
$var reg 1 # data $end
$var reg 1 $ reset $end
$scope module connect_d_ff $end
$var wire 1 % clk $end
$var wire 1 & data $end
$var wire 1 ' reset $end
$var reg 1 ( q $end
$upscope $end
$upscope $end
$enddefinitions $end
#0
$dumpvars
0(
0'
0&
1%
0$
0#
1"
0!
$end
#100
1#
1&
0"
0%
#200
1(
1!
1"
1%
#300
0"
0%
#400
0(
0!
1"
1%
1$
1'
#500
0"
0%
#600
1"
1%
#700
0"
0%
0$
0'
#800
1(
1!
1"
1%
#900
0"
0%
#1000
1"
1%
#1100
0"
0%
#1200
1"
1%
#1300
0"
0%
0#
0&
#1400
0(
0!
1"
1%
#1500
0"
0%
#1600
1"
1%
#1700
0"
0%
#1800
1(
1!
1"
1%
1#
1&
#1900
0"
0%
#2000
0(
0!
1"
1%
0#
0&
